matplotboard/__init__.py
matplotboard/__main__.py
matplotboard/version.py
matplotboard/static/css/default.css
matplotboard/static/icons/android-icon-144x144.png
matplotboard/static/icons/android-icon-192x192.png
matplotboard/static/icons/android-icon-36x36.png
matplotboard/static/icons/android-icon-48x48.png
matplotboard/static/icons/android-icon-72x72.png
matplotboard/static/icons/android-icon-96x96.png
matplotboard/static/icons/apple-icon-114x114.png
matplotboard/static/icons/apple-icon-120x120.png
matplotboard/static/icons/apple-icon-144x144.png
matplotboard/static/icons/apple-icon-152x152.png
matplotboard/static/icons/apple-icon-180x180.png
matplotboard/static/icons/apple-icon-57x57.png
matplotboard/static/icons/apple-icon-60x60.png
matplotboard/static/icons/apple-icon-72x72.png
matplotboard/static/icons/apple-icon-76x76.png
matplotboard/static/icons/apple-icon-precomposed.png
matplotboard/static/icons/apple-icon.png
matplotboard/static/icons/browserconfig.xml
matplotboard/static/icons/favicon-16x16.png
matplotboard/static/icons/favicon-32x32.png
matplotboard/static/icons/favicon-96x96.png
matplotboard/static/icons/favicon.ico
matplotboard/static/icons/manifest.json
matplotboard/static/icons/ms-icon-144x144.png
matplotboard/static/icons/ms-icon-150x150.png
matplotboard/static/icons/ms-icon-310x310.png
matplotboard/static/icons/ms-icon-70x70.png
matplotboard/templates/base.j2
matplotboard/templates/dump.j2
matplotboard/templates/report.j2
matplotboard-1.3.0.dist-info/METADATA
matplotboard-1.3.0.dist-info/WHEEL
matplotboard-1.3.0.dist-info/entry_points.txt
matplotboard-1.3.0.dist-info/RECORD
