Metadata-Version: 2.3
Name: matplotboard
Version: 1.3.0
Summary: Generate simple HTML dashboards using matplotlib
Project-URL: Homepage, https://github.com/cfangmeier/matplotboard
Author-email: Caleb Fangmeier <caleb@fangmeier.tech>
License-Expression: MIT
Classifier: Development Status :: 4 - Beta
Classifier: Intended Audience :: Developers
Classifier: License :: OSI Approved :: MIT License
Classifier: Programming Language :: Python :: 3
Classifier: Programming Language :: Python :: 3.8
Classifier: Programming Language :: Python :: 3.9
Classifier: Programming Language :: Python :: 3.10
Classifier: Programming Language :: Python :: 3.11
Classifier: Programming Language :: Python :: 3.12
Classifier: Topic :: Internet :: WWW/HTTP :: Site Management
Classifier: Topic :: Software Development :: Documentation
Classifier: Topic :: Software Development :: Libraries :: Python Modules
Classifier: Topic :: Text Processing :: Markup :: HTML
Requires-Dist: jinja2>=2.10
Requires-Dist: markdown>=3.0.1
Requires-Dist: matplotlib>=3.0.3
Requires-Dist: openssh-wrapper>=0.4
Requires-Dist: pathos>=0.2.3
Requires-Dist: python-markdown-math>=0.6
Provides-Extra: dev
Requires-Dist: black>=24.0.0; extra == 'dev'
